[
  {
    "__TYPE__": "SharedSliceContent",
    "variation": "default",
    "primary": {
      "heading": {
        "__TYPE__": "StructuredTextContent",
        "value": [
          {
            "type": "heading2",
            "content": {
              "text": "Exciting"
            }
          }
        ]
      },
      "image": {
        "origin": {
          "id": "main",
          "url": "https://images.unsplash.com/photo-1607582278043-57198ac8da43",
          "width": 4024,
          "height": 4024
        },
        "url": "https://images.unsplash.com/photo-1607582278043-57198ac8da43",
        "width": 4024,
        "height": 4024,
        "edit": {
          "zoom": 1,
          "crop": {
            "x": 0,
            "y": 0
          },
          "background": "transparent"
        },
        "credits": null,
        "alt": null,
        "__TYPE__": "ImageContent",
        "thumbnails": {}
      },
      "icon": {
        "__TYPE__": "FieldContent",
        "value": "cycle",
        "type": "Select"
      },
      "subheading": {
        "__TYPE__": "StructuredTextContent",
        "value": [
          {
            "type": "heading3",
            "content": {
              "text": "Every"
            }
          }
        ]
      },
      "body": {
        "__TYPE__": "StructuredTextContent",
        "value": [
          {
            "type": "paragraph",
            "content": {
              "text": "Do nostrud officia velit nostrud elit Lorem dolor enim ex sit eiusmod exercitation reprehenderit anim. Sunt officia est reprehenderit Lorem fugiat ad cupidatat fugiat cillum nulla est veniam cillum magna."
            }
          }
        ]
      },
      "button_text": {
        "__TYPE__": "FieldContent",
        "value": "gentle",
        "type": "Text"
      },
      "button_link": {
        "__TYPE__": "LinkContent",
        "value": {
          "__TYPE__": "ExternalLink",
          "url": "http://twitter.com"
        }
      }
    },
    "items": []
  },
  {
    "__TYPE__": "SharedSliceContent",
    "variation": "reverse",
    "primary": {
      "heading": {
        "__TYPE__": "StructuredTextContent",
        "value": [
          {
            "type": "heading2",
            "content": {
              "text": "Still"
            }
          }
        ]
      },
      "image": {
        "origin": {
          "id": "main",
          "url": "https://images.unsplash.com/photo-1591012911207-0dbac31f37da",
          "width": 4000,
          "height": 4000
        },
        "url": "https://images.unsplash.com/photo-1591012911207-0dbac31f37da",
        "width": 4000,
        "height": 4000,
        "edit": {
          "zoom": 1,
          "crop": {
            "x": 0,
            "y": 0
          },
          "background": "transparent"
        },
        "credits": null,
        "alt": null,
        "__TYPE__": "ImageContent",
        "thumbnails": {}
      },
      "icon": {
        "__TYPE__": "FieldContent",
        "value": "cycle",
        "type": "Select"
      },
      "subheading": {
        "__TYPE__": "StructuredTextContent",
        "value": [
          {
            "type": "heading3",
            "content": {
              "text": "Policeman"
            }
          }
        ]
      },
      "body": {
        "__TYPE__": "StructuredTextContent",
        "value": [
          {
            "type": "paragraph",
            "content": {
              "text": "Ad sit irure ullamco excepteur minim ex esse exercitation adipisicing sunt ex velit et. Qui enim quis ex incididunt non esse sint. Magna excepteur laboris in officia dolore laborum in amet anim aute enim ad cupidatat."
            }
          }
        ]
      },
      "button_text": {
        "__TYPE__": "FieldContent",
        "value": "whale",
        "type": "Text"
      },
      "button_link": {
        "__TYPE__": "LinkContent",
        "value": {
          "__TYPE__": "ExternalLink",
          "url": "http://google.com"
        }
      }
    },
    "items": [
      {
        "__TYPE__": "GroupItemContent",
        "value": []
      }
    ]
  }
]
